{"_comment":"Per-structure overrides for Runic Structures (Runecraft modpack).","_comment2":"Any field omitted uses the global TOML config value.","_comment3":"Override any field per structure. Omitted fields use global TOML config values.","structures":{"_section_vanilla":"=== Vanilla Minecraft ===","minecraft:stronghold":{"spawnCap":14,"eliteChance":0.05,"eliteNamePrefix":"Ancient","enchantmentLevel":3,"darkness":true,"miningFatigue":true,"ambientSounds":true,"persistentMobs":true,"armorTiers":["iron","gold","diamond"],"progressionTier":"late"},"minecraft:fortress":{"spawnCap":10,"eliteChance":0.05,"eliteNamePrefix":"Wither","enchantmentLevel":2,"persistentMobs":true,"armorTiers":["chainmail","iron","gold"],"progressionTier":"mid"},"minecraft:monument":{"spawnCap":8,"eliteChance":0.03,"enchantmentLevel":2,"miningFatigue":true,"armorTiers":["iron","gold"],"progressionTier":"mid"},"minecraft:mansion":{"spawnCap":14,"eliteChance":0.04,"eliteNamePrefix":"Illager","enchantmentLevel":2,"darkness":true,"ambientSounds":true,"armorTiers":["chainmail","iron","gold"],"progressionTier":"mid"},"minecraft:ancient_city":{"spawnCap":10,"eliteChance":0.06,"eliteNamePrefix":"Sculk-Infested","enchantmentLevel":4,"darkness":true,"miningFatigue":true,"slowness":true,"ambientSounds":true,"persistentMobs":true,"armorTiers":["iron","gold","diamond"],"progressionTier":"late"},"minecraft:desert_pyramid":{"spawnCap":3,"enchantmentLevel":1,"armorTiers":["leather","chainmail"],"progressionTier":"early"},"minecraft:jungle_pyramid":{"spawnCap":3,"enchantmentLevel":1,"slowness":true,"armorTiers":["leather","chainmail"],"progressionTier":"early"},"minecraft:pillager_outpost":{"spawnCap":5,"eliteNamePrefix":"Commander","persistentMobs":true,"armorTiers":["chainmail","iron"],"progressionTier":"early"},"minecraft:bastion_remnant":{"spawnCap":14,"eliteChance":0.04,"enchantmentLevel":3,"armorTiers":["iron","gold","diamond"],"progressionTier":"mid"},"minecraft:end_city":{"spawnCap":10,"eliteChance":0.04,"eliteNamePrefix":"Corrupted","enchantmentLevel":3,"slowness":true,"persistentMobs":true,"armorTiers":["iron","gold","diamond"],"progressionTier":"late"},"minecraft:mineshaft":{"spawnCap":4,"eliteNamePrefix":"Deep","enchantmentLevel":1,"darkness":true,"miningFatigue":true,"ambientSounds":true,"armorTiers":["leather","chainmail"],"progressionTier":"early"},"minecraft:ruined_portal":{"spawnCap":2,"enchantmentLevel":0},"minecraft:swamp_hut":{"spawnCap":2,"eliteNamePrefix":"Hexed","enchantmentLevel":0,"progressionTier":"early"},"_section_yungs":"=== YUNG's Better Series ===","betterfortresses:fortress":{"spawnCap":16,"eliteChance":0.06,"eliteNamePrefix":"Wither","enchantmentLevel":3,"persistentMobs":true,"darkness":true,"ambientSounds":true,"armorTiers":["iron","gold","diamond"],"progressionTier":"mid"},"betteroceanmonuments:ocean_monument":{"spawnCap":12,"eliteChance":0.04,"enchantmentLevel":3,"miningFatigue":true,"armorTiers":["iron","gold"],"progressionTier":"mid"},"betterwitchhuts:witch_hut":{"spawnCap":3,"eliteNamePrefix":"Hexed","enchantmentLevel":1,"armorTiers":["leather","chainmail"],"progressionTier":"early"},"betterwitchhuts:witch_circle":{"spawnCap":3,"eliteNamePrefix":"Hexed","enchantmentLevel":1,"ambientSounds":true,"armorTiers":["leather","chainmail"],"progressionTier":"early"},"betterdungeons:skeleton_dungeon":{"spawnCap":6,"eliteChance":0.03,"eliteNamePrefix":"Cursed","enchantmentLevel":2,"darkness":true,"ambientSounds":true,"armorTiers":["chainmail","iron"],"progressionTier":"mid"},"betterdungeons:zombie_dungeon":{"spawnCap":6,"eliteChance":0.03,"eliteNamePrefix":"Cursed","enchantmentLevel":2,"darkness":true,"ambientSounds":true,"armorTiers":["chainmail","iron"],"progressionTier":"mid"},"betterdungeons:spider_dungeon":{"spawnCap":6,"eliteChance":0.03,"eliteNamePrefix":"Feral","enchantmentLevel":1,"darkness":true,"ambientSounds":true,"progressionTier":"mid"},"betterdungeons:small_dungeon":{"spawnCap":3,"enchantmentLevel":1,"darkness":true,"ambientSounds":true,"armorTiers":["leather","chainmail"],"progressionTier":"early"},"betterdungeons:small_nether_dungeon":{"spawnCap":3,"eliteNamePrefix":"Wither","enchantmentLevel":1,"armorTiers":["chainmail","iron"],"progressionTier":"mid"},"_section_hopo":"=== Hopo Better Mineshaft + Underwater Ruins ===","hopo:mineshaft/oak_mineshaft":{"spawnCap":4,"eliteNamePrefix":"Deep","enchantmentLevel":1,"darkness":true,"miningFatigue":true,"ambientSounds":true,"armorTiers":["leather","chainmail"],"progressionTier":"early"},"hopo:mineshaft/acacia_mineshaft":{"spawnCap":4,"eliteNamePrefix":"Deep","enchantmentLevel":1,"darkness":true,"miningFatigue":true,"ambientSounds":true,"armorTiers":["leather","chainmail"],"progressionTier":"early"},"hopo:mineshaft/bamboo_mineshaft":{"spawnCap":4,"eliteNamePrefix":"Deep","enchantmentLevel":1,"darkness":true,"miningFatigue":true,"ambientSounds":true,"armorTiers":["leather","chainmail"],"progressionTier":"early"},"hopo:mineshaft/birch_mineshaft":{"spawnCap":4,"eliteNamePrefix":"Deep","enchantmentLevel":1,"darkness":true,"miningFatigue":true,"ambientSounds":true,"armorTiers":["leather","chainmail"],"progressionTier":"early"},"hopo:mineshaft/cherry_mineshaft":{"spawnCap":4,"eliteNamePrefix":"Deep","enchantmentLevel":1,"darkness":true,"miningFatigue":true,"ambientSounds":true,"armorTiers":["leather","chainmail"],"progressionTier":"early"},"hopo:mineshaft/dark_oak_mineshaft":{"spawnCap":4,"eliteNamePrefix":"Deep","enchantmentLevel":1,"darkness":true,"miningFatigue":true,"ambientSounds":true,"armorTiers":["leather","chainmail"],"progressionTier":"early"},"hopo:mineshaft/deepslate_mineshaft":{"spawnCap":4,"eliteNamePrefix":"Deep","enchantmentLevel":1,"darkness":true,"miningFatigue":true,"ambientSounds":true,"armorTiers":["leather","chainmail"],"progressionTier":"early"},"hopo:mineshaft/jungle_mineshaft":{"spawnCap":4,"eliteNamePrefix":"Deep","enchantmentLevel":1,"darkness":true,"miningFatigue":true,"ambientSounds":true,"armorTiers":["leather","chainmail"],"progressionTier":"early"},"hopo:mineshaft/mangrove_mineshaft":{"spawnCap":4,"eliteNamePrefix":"Deep","enchantmentLevel":1,"darkness":true,"miningFatigue":true,"ambientSounds":true,"armorTiers":["leather","chainmail"],"progressionTier":"early"},"hopo:mineshaft/mud_mineshaft":{"spawnCap":4,"eliteNamePrefix":"Deep","enchantmentLevel":1,"darkness":true,"miningFatigue":true,"ambientSounds":true,"armorTiers":["leather","chainmail"],"progressionTier":"early"},"hopo:mineshaft/spruce_mineshaft":{"spawnCap":4,"eliteNamePrefix":"Deep","enchantmentLevel":1,"darkness":true,"miningFatigue":true,"ambientSounds":true,"armorTiers":["leather","chainmail"],"progressionTier":"early"},"hopo:mineshaft/stone_mineshaft":{"spawnCap":4,"eliteNamePrefix":"Deep","enchantmentLevel":1,"darkness":true,"miningFatigue":true,"ambientSounds":true,"armorTiers":["leather","chainmail"],"progressionTier":"early"},"hopo:mineshaft/biomes/dripstone_mineshaft":{"spawnCap":5,"eliteNamePrefix":"Deep","enchantmentLevel":1,"darkness":true,"miningFatigue":true,"ambientSounds":true,"armorTiers":["chainmail","iron"],"progressionTier":"mid"},"hopo:mineshaft/biomes/lush_mineshaft":{"spawnCap":5,"eliteNamePrefix":"Feral","enchantmentLevel":1,"miningFatigue":true,"ambientSounds":true,"armorTiers":["chainmail","iron"],"progressionTier":"mid"},"hopo:underwater/underwater_city":{"spawnCap":8,"eliteChance":0.04,"eliteNamePrefix":"Dread","enchantmentLevel":2,"miningFatigue":true,"armorTiers":["iron","gold"],"progressionTier":"mid"},"hopo:underwater/underwater_small_ruins":{"spawnCap":2,"enchantmentLevel":0,"progressionTier":"early"},"hopo:underwater/underwater_warm_small_ruins":{"spawnCap":2,"enchantmentLevel":0,"progressionTier":"early"},"_section_wda":"=== When Dungeons Arise ===","dungeons_arise:abandoned_temple":{"spawnCap":3,"eliteNamePrefix":"Fallen","enchantmentLevel":1,"ambientSounds":true,"armorTiers":["leather","chainmail"],"progressionTier":"early"},"dungeons_arise:lighthouse":{"spawnCap":2,"enchantmentLevel":0,"progressionTier":"early"},"dungeons_arise:fishing_hut":{"spawnCap":1,"enchantmentLevel":0,"progressionTier":"early"},"dungeons_arise:wishing_well":{"spawnCap":1,"enchantmentLevel":0,"progressionTier":"early"},"dungeons_arise:jungle_tree_house":{"spawnCap":2,"eliteNamePrefix":"Feral","enchantmentLevel":0,"progressionTier":"early"},"dungeons_arise:bathhouse":{"spawnCap":2,"enchantmentLevel":0,"progressionTier":"early"},"dungeons_arise:greenwood_pub":{"spawnCap":2,"enchantmentLevel":0,"progressionTier":"early"},"dungeons_arise:illager_campsite":{"spawnCap":3,"eliteNamePrefix":"Commander","enchantmentLevel":1,"persistentMobs":true,"armorTiers":["chainmail","iron"],"progressionTier":"early"},"dungeons_arise:merchant_campsite":{"spawnCap":3,"enchantmentLevel":0,"progressionTier":"early"},"dungeons_arise:illager_windmill":{"spawnCap":4,"eliteNamePrefix":"Commander","enchantmentLevel":1,"armorTiers":["chainmail","iron"],"progressionTier":"early"},"dungeons_arise:giant_mushroom":{"spawnCap":3,"enchantmentLevel":0,"progressionTier":"early"},"dungeons_arise:mushroom_house":{"spawnCap":3,"eliteNamePrefix":"Feral","enchantmentLevel":1,"armorTiers":["chainmail","iron"],"progressionTier":"early"},"dungeons_arise:mushroom_village":{"spawnCap":5,"eliteNamePrefix":"Feral","enchantmentLevel":1,"armorTiers":["chainmail","iron"],"progressionTier":"early"},"dungeons_arise:illager_galley":{"spawnCap":5,"eliteNamePrefix":"Dread","enchantmentLevel":1,"armorTiers":["chainmail","iron"],"progressionTier":"mid"},"dungeons_arise:undead_pirate_ship":{"spawnCap":5,"eliteNamePrefix":"Cursed","enchantmentLevel":1,"darkness":true,"armorTiers":["chainmail","iron"],"progressionTier":"mid"},"dungeons_arise:typhon":{"spawnCap":4,"eliteNamePrefix":"Dread","enchantmentLevel":1,"progressionTier":"mid"},"dungeons_arise:small_blimp":{"spawnCap":3,"eliteNamePrefix":"Commander","enchantmentLevel":1,"progressionTier":"early"},"dungeons_arise:bandit_village":{"spawnCap":6,"eliteNamePrefix":"Commander","enchantmentLevel":1,"persistentMobs":true,"armorTiers":["leather","chainmail","iron"],"progressionTier":"mid"},"dungeons_arise:ceryneian_hind":{"spawnCap":5,"enchantmentLevel":1,"progressionTier":"mid"},"dungeons_arise:bandit_towers":{"spawnCap":6,"eliteNamePrefix":"Commander","enchantmentLevel":2,"darkness":true,"armorTiers":["chainmail","iron"],"progressionTier":"mid"},"dungeons_arise:mushroom_mines":{"spawnCap":6,"eliteNamePrefix":"Deep","enchantmentLevel":1,"darkness":true,"miningFatigue":true,"ambientSounds":true,"armorTiers":["chainmail","iron"],"progressionTier":"mid"},"dungeons_arise:monastery":{"spawnCap":7,"eliteNamePrefix":"Fallen","enchantmentLevel":2,"ambientSounds":true,"armorTiers":["chainmail","iron","gold"],"progressionTier":"mid"},"dungeons_arise:coliseum":{"spawnCap":8,"eliteChance":0.04,"eliteNamePrefix":"Commander","enchantmentLevel":2,"armorTiers":["iron","gold"],"progressionTier":"mid"},"dungeons_arise:thornborn_towers":{"spawnCap":7,"eliteNamePrefix":"Corrupted","enchantmentLevel":2,"darkness":true,"armorTiers":["iron","gold"],"progressionTier":"mid"},"dungeons_arise:illager_corsair":{"spawnCap":7,"eliteNamePrefix":"Dread","enchantmentLevel":2,"armorTiers":["iron","gold"],"progressionTier":"mid"},"dungeons_arise:mining_system":{"spawnCap":8,"eliteNamePrefix":"Deep","enchantmentLevel":2,"darkness":true,"miningFatigue":true,"ambientSounds":true,"armorTiers":["chainmail","iron"],"progressionTier":"mid"},"dungeons_arise:heavenly_rider":{"spawnCap":7,"eliteNamePrefix":"Fallen","enchantmentLevel":2,"armorTiers":["iron","gold"],"progressionTier":"mid"},"dungeons_arise:heavenly_conqueror":{"spawnCap":8,"eliteNamePrefix":"Fallen","enchantmentLevel":2,"armorTiers":["iron","gold"],"progressionTier":"late"},"dungeons_arise:scorched_mines":{"spawnCap":7,"eliteNamePrefix":"Wither","enchantmentLevel":2,"darkness":true,"miningFatigue":true,"ambientSounds":true,"armorTiers":["iron","gold"],"progressionTier":"mid"},"dungeons_arise:illager_fort":{"spawnCap":14,"eliteChance":0.05,"eliteNamePrefix":"Commander","enchantmentLevel":3,"persistentMobs":true,"darkness":true,"ambientSounds":true,"armorTiers":["iron","gold","diamond"],"progressionTier":"late"},"dungeons_arise:shiraz_palace":{"spawnCap":16,"eliteChance":0.05,"eliteNamePrefix":"Lord","enchantmentLevel":3,"darkness":true,"ambientSounds":true,"armorTiers":["iron","gold","diamond"],"progressionTier":"late"},"dungeons_arise:keep_kayra":{"spawnCap":12,"eliteChance":0.05,"eliteNamePrefix":"Lord","enchantmentLevel":3,"darkness":true,"ambientSounds":true,"armorTiers":["iron","gold","diamond"],"progressionTier":"late"},"dungeons_arise:heavenly_challenger":{"spawnCap":14,"eliteChance":0.05,"eliteNamePrefix":"Fallen","enchantmentLevel":3,"armorTiers":["iron","gold","diamond"],"progressionTier":"late"},"dungeons_arise:mechanical_nest":{"spawnCap":12,"eliteChance":0.04,"eliteNamePrefix":"Corrupted","enchantmentLevel":3,"darkness":true,"miningFatigue":true,"ambientSounds":true,"armorTiers":["iron","gold","diamond"],"progressionTier":"late"},"dungeons_arise:foundry":{"spawnCap":12,"eliteChance":0.05,"eliteNamePrefix":"Deep","enchantmentLevel":3,"darkness":true,"miningFatigue":true,"ambientSounds":true,"armorTiers":["iron","gold","diamond"],"progressionTier":"late"},"dungeons_arise:infested_temple":{"spawnCap":10,"eliteChance":0.04,"eliteNamePrefix":"Corrupted","enchantmentLevel":3,"darkness":true,"ambientSounds":true,"armorTiers":["iron","gold","diamond"],"progressionTier":"late"},"dungeons_arise:plague_asylum":{"spawnCap":12,"eliteChance":0.05,"eliteNamePrefix":"Corrupted","enchantmentLevel":3,"darkness":true,"slowness":true,"ambientSounds":true,"armorTiers":["iron","gold","diamond"],"progressionTier":"late"},"dungeons_arise:aviary":{"spawnCap":10,"eliteChance":0.06,"eliteNamePrefix":"Corrupted","enchantmentLevel":4,"slowness":true,"persistentMobs":true,"armorTiers":["iron","diamond","netherite"],"progressionTier":"veteran"},"_section_wda_ss":"=== When Dungeons Arise: Seven Seas ===","dungeons_arise_seven_seas:corsair_corvette":{"spawnCap":4,"eliteNamePrefix":"Dread","enchantmentLevel":1,"armorTiers":["chainmail","iron"],"progressionTier":"mid"},"dungeons_arise_seven_seas:pirate_junk":{"spawnCap":3,"eliteNamePrefix":"Dread","enchantmentLevel":1,"armorTiers":["leather","chainmail"],"progressionTier":"early"},"dungeons_arise_seven_seas:small_yacht":{"spawnCap":2,"enchantmentLevel":0,"progressionTier":"early"},"dungeons_arise_seven_seas:unicorn_galleon":{"spawnCap":6,"eliteNamePrefix":"Dread","enchantmentLevel":2,"armorTiers":["chainmail","iron","gold"],"progressionTier":"mid"},"dungeons_arise_seven_seas:victory_frigate":{"spawnCap":8,"eliteChance":0.04,"eliteNamePrefix":"Dread","enchantmentLevel":2,"persistentMobs":true,"armorTiers":["iron","gold"],"progressionTier":"mid"},"_section_dnt":"=== Dungeons and Taverns (nova_structures) ===","nova_structures:firewatch_tower_birch":{"spawnCap":3,"enchantmentLevel":0,"progressionTier":"early"},"nova_structures:firewatch_tower_cherry":{"spawnCap":3,"enchantmentLevel":0,"progressionTier":"early"},"nova_structures:firewatch_tower_dark_oak":{"spawnCap":3,"enchantmentLevel":0,"progressionTier":"early"},"nova_structures:firewatch_tower_forest":{"spawnCap":3,"enchantmentLevel":0,"progressionTier":"early"},"nova_structures:firewatch_tower_jungle":{"spawnCap":3,"enchantmentLevel":0,"progressionTier":"early"},"nova_structures:firewatch_tower_mangrove":{"spawnCap":3,"enchantmentLevel":0,"progressionTier":"early"},"nova_structures:firewatch_tower_savanna":{"spawnCap":3,"enchantmentLevel":0,"progressionTier":"early"},"nova_structures:firewatch_tower_swamp":{"spawnCap":3,"enchantmentLevel":0,"progressionTier":"early"},"nova_structures:firewatch_tower_taiga":{"spawnCap":3,"enchantmentLevel":0,"progressionTier":"early"},"nova_structures:tavern_acacia":{"spawnCap":2,"enchantmentLevel":0,"progressionTier":"early"},"nova_structures:tavern_birch":{"spawnCap":2,"enchantmentLevel":0,"progressionTier":"early"},"nova_structures:tavern_cherry":{"spawnCap":2,"enchantmentLevel":0,"progressionTier":"early"},"nova_structures:tavern_dark_oak":{"spawnCap":2,"enchantmentLevel":0,"progressionTier":"early"},"nova_structures:tavern_desert":{"spawnCap":2,"enchantmentLevel":0,"progressionTier":"early"},"nova_structures:tavern_jungle":{"spawnCap":2,"enchantmentLevel":0,"progressionTier":"early"},"nova_structures:tavern_mangrove":{"spawnCap":2,"enchantmentLevel":0,"progressionTier":"early"},"nova_structures:tavern_oak":{"spawnCap":2,"enchantmentLevel":0,"progressionTier":"early"},"nova_structures:tavern_snowy":{"spawnCap":2,"enchantmentLevel":0,"progressionTier":"early"},"nova_structures:tavern_spruce":{"spawnCap":2,"enchantmentLevel":0,"progressionTier":"early"},"nova_structures:tavern_swamp":{"spawnCap":2,"enchantmentLevel":0,"progressionTier":"early"},"nova_structures:well_birch":{"spawnCap":1,"enchantmentLevel":0,"progressionTier":"early"},"nova_structures:well_dark_oak":{"spawnCap":1,"enchantmentLevel":0,"progressionTier":"early"},"nova_structures:well_jungle":{"spawnCap":1,"enchantmentLevel":0,"progressionTier":"early"},"nova_structures:well_oak":{"spawnCap":1,"enchantmentLevel":0,"progressionTier":"early"},"nova_structures:well_savana":{"spawnCap":1,"enchantmentLevel":0,"progressionTier":"early"},"nova_structures:well_spruce":{"spawnCap":1,"enchantmentLevel":0,"progressionTier":"early"},"nova_structures:village_jungle":{"spawnCap":3,"enchantmentLevel":0,"progressionTier":"early"},"nova_structures:village_swamp":{"spawnCap":3,"enchantmentLevel":0,"progressionTier":"early"},"nova_structures:desert_ruins":{"spawnCap":3,"enchantmentLevel":1,"progressionTier":"early"},"nova_structures:jungle_ruins":{"spawnCap":3,"eliteNamePrefix":"Feral","enchantmentLevel":1,"progressionTier":"early"},"nova_structures:wild_ruin":{"spawnCap":3,"enchantmentLevel":1,"progressionTier":"early"},"nova_structures:conduit_ruin":{"spawnCap":3,"enchantmentLevel":1,"progressionTier":"early"},"nova_structures:ruin_town":{"spawnCap":5,"eliteNamePrefix":"Cursed","enchantmentLevel":1,"ambientSounds":true,"armorTiers":["leather","chainmail"],"progressionTier":"early"},"nova_structures:creeping_crypt":{"spawnCap":5,"eliteNamePrefix":"Cursed","enchantmentLevel":2,"darkness":true,"ambientSounds":true,"armorTiers":["chainmail","iron"],"progressionTier":"mid"},"nova_structures:undead_crypt":{"spawnCap":5,"eliteNamePrefix":"Cursed","enchantmentLevel":2,"darkness":true,"ambientSounds":true,"armorTiers":["chainmail","iron"],"progressionTier":"mid"},"nova_structures:illager_camp":{"spawnCap":4,"eliteNamePrefix":"Commander","enchantmentLevel":1,"persistentMobs":true,"armorTiers":["chainmail","iron"],"progressionTier":"early"},"nova_structures:illager_hideout":{"spawnCap":4,"eliteNamePrefix":"Commander","enchantmentLevel":1,"darkness":true,"armorTiers":["chainmail","iron"],"progressionTier":"mid"},"nova_structures:illager_manor":{"spawnCap":8,"eliteChance":0.04,"eliteNamePrefix":"Commander","enchantmentLevel":2,"darkness":true,"ambientSounds":true,"armorTiers":["chainmail","iron","gold"],"progressionTier":"mid"},"nova_structures:badlands_miner_outpost":{"spawnCap":4,"eliteNamePrefix":"Deep","enchantmentLevel":1,"armorTiers":["chainmail","iron"],"progressionTier":"early"},"nova_structures:bunker":{"spawnCap":4,"eliteNamePrefix":"Deep","enchantmentLevel":1,"darkness":true,"ambientSounds":true,"armorTiers":["chainmail","iron"],"progressionTier":"mid"},"nova_structures:stray_fort":{"spawnCap":5,"eliteNamePrefix":"Commander","enchantmentLevel":1,"armorTiers":["chainmail","iron"],"progressionTier":"mid"},"nova_structures:mangrove_witch_hut":{"spawnCap":2,"eliteNamePrefix":"Hexed","enchantmentLevel":0,"progressionTier":"early"},"nova_structures:underground_house":{"spawnCap":2,"enchantmentLevel":0,"darkness":true,"progressionTier":"early"},"nova_structures:witch_villa":{"spawnCap":4,"eliteNamePrefix":"Hexed","enchantmentLevel":1,"ambientSounds":true,"armorTiers":["chainmail","iron"],"progressionTier":"mid"},"nova_structures:donjon":{"spawnCap":6,"eliteNamePrefix":"Wither","enchantmentLevel":2,"darkness":true,"ambientSounds":true,"armorTiers":["iron","gold"],"progressionTier":"mid"},"nova_structures:hamlet":{"spawnCap":4,"eliteNamePrefix":"Wither","enchantmentLevel":1,"armorTiers":["chainmail","iron"],"progressionTier":"mid"},"nova_structures:nether_keep":{"spawnCap":8,"eliteChance":0.04,"eliteNamePrefix":"Wither","enchantmentLevel":3,"darkness":true,"ambientSounds":true,"persistentMobs":true,"armorTiers":["iron","gold","diamond"],"progressionTier":"late"},"nova_structures:nether_port":{"spawnCap":5,"eliteNamePrefix":"Wither","enchantmentLevel":2,"armorTiers":["chainmail","iron","gold"],"progressionTier":"mid"},"nova_structures:nether_skeleton_tower_basalt":{"spawnCap":4,"eliteNamePrefix":"Wither","enchantmentLevel":2,"armorTiers":["chainmail","iron"],"progressionTier":"mid"},"nova_structures:nether_skeleton_tower_crimson":{"spawnCap":4,"eliteNamePrefix":"Wither","enchantmentLevel":2,"armorTiers":["chainmail","iron"],"progressionTier":"mid"},"nova_structures:nether_skeleton_tower_soul":{"spawnCap":4,"eliteNamePrefix":"Wither","enchantmentLevel":2,"armorTiers":["chainmail","iron"],"progressionTier":"mid"},"nova_structures:nether_skeleton_tower_warped":{"spawnCap":4,"eliteNamePrefix":"Wither","enchantmentLevel":2,"armorTiers":["chainmail","iron"],"progressionTier":"mid"},"nova_structures:piglin_camp":{"spawnCap":4,"eliteNamePrefix":"Wither","enchantmentLevel":1,"armorTiers":["gold","iron"],"progressionTier":"mid"},"nova_structures:piglin_outstation":{"spawnCap":3,"eliteNamePrefix":"Wither","enchantmentLevel":1,"armorTiers":["gold"],"progressionTier":"mid"},"nova_structures:skeleton_camp_crimson":{"spawnCap":4,"eliteNamePrefix":"Wither","enchantmentLevel":2,"armorTiers":["chainmail","iron"],"progressionTier":"mid"},"nova_structures:skeleton_camp_soul":{"spawnCap":4,"eliteNamePrefix":"Wither","enchantmentLevel":2,"armorTiers":["chainmail","iron"],"progressionTier":"mid"},"nova_structures:skeleton_camp_warped":{"spawnCap":4,"eliteNamePrefix":"Wither","enchantmentLevel":2,"armorTiers":["chainmail","iron"],"progressionTier":"mid"},"nova_structures:skeleton_camp_waste":{"spawnCap":4,"eliteNamePrefix":"Wither","enchantmentLevel":2,"armorTiers":["chainmail","iron"],"progressionTier":"mid"},"_section_medieval":"=== Medieval Buildings ===","medieval_buildings:fort":{"spawnCap":8,"eliteChance":0.04,"eliteNamePrefix":"Lord","enchantmentLevel":2,"persistentMobs":true,"ambientSounds":true,"armorTiers":["iron","gold"],"progressionTier":"mid"},"medieval_buildings:house_1":{"spawnCap":2,"enchantmentLevel":0,"progressionTier":"early"},"medieval_buildings:house_2":{"spawnCap":2,"enchantmentLevel":0,"progressionTier":"early"},"medieval_buildings:tower":{"spawnCap":4,"eliteNamePrefix":"Lord","enchantmentLevel":1,"darkness":true,"armorTiers":["chainmail","iron"],"progressionTier":"mid"},"medieval_buildings:ship":{"spawnCap":3,"eliteNamePrefix":"Dread","enchantmentLevel":1,"armorTiers":["chainmail","iron"],"progressionTier":"early"},"medieval_nether:castle":{"spawnCap":10,"eliteChance":0.05,"eliteNamePrefix":"Wither","enchantmentLevel":3,"darkness":true,"ambientSounds":true,"persistentMobs":true,"armorTiers":["iron","gold","diamond"],"progressionTier":"late"},"medieval_nether:dome":{"spawnCap":5,"eliteNamePrefix":"Wither","enchantmentLevel":2,"armorTiers":["iron","gold"],"progressionTier":"mid"},"medieval_nether:house":{"spawnCap":3,"eliteNamePrefix":"Wither","enchantmentLevel":1,"armorTiers":["chainmail","iron"],"progressionTier":"mid"},"medieval_nether:ship":{"spawnCap":4,"eliteNamePrefix":"Wither","enchantmentLevel":2,"armorTiers":["iron","gold"],"progressionTier":"mid"},"medieval_nether:shrine":{"spawnCap":2,"eliteNamePrefix":"Wither","enchantmentLevel":1,"ambientSounds":true,"progressionTier":"mid"},"_section_moogs":"=== Moog's Mods ===","mmv:village_jungle":{"spawnCap":3,"enchantmentLevel":0,"progressionTier":"early"},"mmv:village_swamp":{"spawnCap":3,"enchantmentLevel":0,"progressionTier":"early"},"mns:very_small_blackstone":{"spawnCap":2,"eliteNamePrefix":"Wither","enchantmentLevel":1,"progressionTier":"mid"},"mns:very_small_blackstone_2":{"spawnCap":2,"eliteNamePrefix":"Wither","enchantmentLevel":1,"progressionTier":"mid"},"mns:very_small_blackstone_3":{"spawnCap":2,"eliteNamePrefix":"Wither","enchantmentLevel":1,"progressionTier":"mid"},"mns:very_small_blackstone_4":{"spawnCap":2,"eliteNamePrefix":"Wither","enchantmentLevel":1,"progressionTier":"mid"},"mns:very_small_nether_brick":{"spawnCap":2,"eliteNamePrefix":"Wither","enchantmentLevel":1,"progressionTier":"mid"},"mns:very_small_nether_brick_2":{"spawnCap":2,"eliteNamePrefix":"Wither","enchantmentLevel":1,"progressionTier":"mid"},"mns:very_small_nether_brick_3":{"spawnCap":2,"eliteNamePrefix":"Wither","enchantmentLevel":1,"progressionTier":"mid"},"mns:small_nether_brick":{"spawnCap":3,"eliteNamePrefix":"Wither","enchantmentLevel":1,"armorTiers":["chainmail","iron"],"progressionTier":"mid"},"mns:smoking_shrine":{"spawnCap":3,"eliteNamePrefix":"Wither","enchantmentLevel":1,"ambientSounds":true,"progressionTier":"mid"},"mns:circle_blackstone":{"spawnCap":3,"eliteNamePrefix":"Wither","enchantmentLevel":1,"ambientSounds":true,"progressionTier":"mid"},"mns:circle_nether_brick":{"spawnCap":3,"eliteNamePrefix":"Wither","enchantmentLevel":1,"progressionTier":"mid"},"mns:medium_blackstone":{"spawnCap":4,"eliteNamePrefix":"Wither","enchantmentLevel":1,"armorTiers":["chainmail","iron"],"progressionTier":"mid"},"mns:medium_crimson_fungus":{"spawnCap":3,"eliteNamePrefix":"Feral","enchantmentLevel":1,"progressionTier":"mid"},"mns:medium_crimson_fungus_2":{"spawnCap":3,"eliteNamePrefix":"Feral","enchantmentLevel":1,"progressionTier":"mid"},"mns:medium_crimson_well":{"spawnCap":3,"eliteNamePrefix":"Wither","enchantmentLevel":1,"progressionTier":"mid"},"mns:medium_warped_fungus":{"spawnCap":3,"eliteNamePrefix":"Feral","enchantmentLevel":1,"progressionTier":"mid"},"mns:medium_warped_fungus_2":{"spawnCap":3,"eliteNamePrefix":"Feral","enchantmentLevel":1,"progressionTier":"mid"},"mns:medium_warped_well":{"spawnCap":3,"eliteNamePrefix":"Wither","enchantmentLevel":1,"progressionTier":"mid"},"mns:large_blackstone_pillars":{"spawnCap":4,"eliteNamePrefix":"Wither","enchantmentLevel":2,"armorTiers":["chainmail","iron","gold"],"progressionTier":"mid"},"mns:large_blackstone_walls":{"spawnCap":4,"eliteNamePrefix":"Wither","enchantmentLevel":2,"armorTiers":["chainmail","iron","gold"],"progressionTier":"mid"},"mns:large_nether_brick":{"spawnCap":4,"eliteNamePrefix":"Wither","enchantmentLevel":2,"armorTiers":["iron","gold"],"progressionTier":"mid"},"mns:grave_yard":{"spawnCap":4,"eliteNamePrefix":"Cursed","enchantmentLevel":2,"ambientSounds":true,"armorTiers":["chainmail","iron"],"progressionTier":"mid"},"mns:lava_pool":{"spawnCap":3,"eliteNamePrefix":"Wither","enchantmentLevel":1,"progressionTier":"mid"},"mns:warped_pool":{"spawnCap":3,"eliteNamePrefix":"Wither","enchantmentLevel":1,"progressionTier":"mid"},"mns:medium_house":{"spawnCap":4,"eliteNamePrefix":"Wither","enchantmentLevel":2,"darkness":true,"armorTiers":["iron","gold"],"progressionTier":"mid"},"mns:medium_house_2":{"spawnCap":4,"eliteNamePrefix":"Wither","enchantmentLevel":2,"darkness":true,"armorTiers":["iron","gold"],"progressionTier":"mid"},"mtr:desert_temple":{"spawnCap":4,"eliteNamePrefix":"Fallen","enchantmentLevel":1,"armorTiers":["chainmail","iron"],"progressionTier":"early"},"mtr:jungle_temple":{"spawnCap":4,"eliteNamePrefix":"Feral","enchantmentLevel":1,"slowness":true,"armorTiers":["chainmail","iron"],"progressionTier":"early"},"mtr:badlands_temple":{"spawnCap":4,"eliteNamePrefix":"Fallen","enchantmentLevel":1,"armorTiers":["chainmail","iron"],"progressionTier":"early"},"mtr:nether_temple":{"spawnCap":6,"eliteNamePrefix":"Wither","enchantmentLevel":2,"darkness":true,"ambientSounds":true,"armorTiers":["iron","gold"],"progressionTier":"mid"},"mtr:ocean_temple":{"spawnCap":5,"eliteNamePrefix":"Dread","enchantmentLevel":2,"miningFatigue":true,"armorTiers":["iron","gold"],"progressionTier":"mid"},"mtr:stronghold":{"spawnCap":12,"eliteChance":0.05,"eliteNamePrefix":"Ancient","enchantmentLevel":3,"darkness":true,"miningFatigue":true,"ambientSounds":true,"persistentMobs":true,"armorTiers":["iron","gold","diamond"],"progressionTier":"late"},"_section_underground":"=== Underground Rooms ===","underground_rooms:jungle_main_room":{"spawnCap":5,"eliteNamePrefix":"Feral","enchantmentLevel":2,"darkness":true,"ambientSounds":true,"armorTiers":["chainmail","iron"],"progressionTier":"mid"},"underground_rooms:undead_main_room":{"spawnCap":5,"eliteNamePrefix":"Cursed","enchantmentLevel":2,"darkness":true,"ambientSounds":true,"armorTiers":["chainmail","iron"],"progressionTier":"mid"},"underground_rooms:mainroom1":{"spawnCap":5,"eliteNamePrefix":"Deep","enchantmentLevel":2,"darkness":true,"ambientSounds":true,"armorTiers":["chainmail","iron"],"progressionTier":"mid"},"underground_rooms:library":{"spawnCap":6,"eliteChance":0.03,"eliteNamePrefix":"Arcane","enchantmentLevel":2,"darkness":true,"ambientSounds":true,"armorTiers":["chainmail","iron","gold"],"progressionTier":"mid"},"underground_rooms:alchemy_room":{"spawnCap":2,"eliteNamePrefix":"Arcane","enchantmentLevel":1,"darkness":true,"ambientSounds":true,"progressionTier":"mid"},"underground_rooms:blacksmith_room1":{"spawnCap":2,"eliteNamePrefix":"Deep","enchantmentLevel":1,"darkness":true,"progressionTier":"mid"},"underground_rooms:catacombs":{"spawnCap":3,"eliteNamePrefix":"Cursed","enchantmentLevel":2,"darkness":true,"ambientSounds":true,"armorTiers":["chainmail","iron"],"progressionTier":"mid"},"underground_rooms:desert_crypt":{"spawnCap":3,"eliteNamePrefix":"Cursed","enchantmentLevel":2,"darkness":true,"ambientSounds":true,"armorTiers":["chainmail","iron"],"progressionTier":"mid"},"underground_rooms:dungeon":{"spawnCap":3,"eliteNamePrefix":"Deep","enchantmentLevel":1,"darkness":true,"ambientSounds":true,"progressionTier":"mid"},"underground_rooms:enchanting_room":{"spawnCap":2,"eliteNamePrefix":"Arcane","enchantmentLevel":2,"darkness":true,"progressionTier":"mid"},"underground_rooms:end_room":{"spawnCap":3,"eliteNamePrefix":"Corrupted","enchantmentLevel":3,"darkness":true,"ambientSounds":true,"armorTiers":["iron","gold"],"progressionTier":"late"},"underground_rooms:hidden_temple":{"spawnCap":3,"eliteNamePrefix":"Fallen","enchantmentLevel":2,"darkness":true,"ambientSounds":true,"armorTiers":["chainmail","iron"],"progressionTier":"mid"},"underground_rooms:library1":{"spawnCap":2,"eliteNamePrefix":"Arcane","enchantmentLevel":2,"darkness":true,"progressionTier":"mid"},"underground_rooms:mining_storage_room":{"spawnCap":2,"eliteNamePrefix":"Deep","enchantmentLevel":1,"darkness":true,"miningFatigue":true,"progressionTier":"mid"},"underground_rooms:throne_room":{"spawnCap":3,"eliteChance":0.04,"eliteNamePrefix":"Lord","enchantmentLevel":2,"darkness":true,"ambientSounds":true,"armorTiers":["iron","gold"],"progressionTier":"mid"},"underground_rooms:torture_chamber":{"spawnCap":3,"eliteNamePrefix":"Cursed","enchantmentLevel":2,"darkness":true,"ambientSounds":true,"slowness":true,"armorTiers":["chainmail","iron"],"progressionTier":"mid"},"underground_rooms:treasure_room":{"spawnCap":3,"eliteNamePrefix":"Deep","enchantmentLevel":2,"darkness":true,"miningFatigue":true,"armorTiers":["iron","gold"],"progressionTier":"mid"},"underground_rooms:wine_cellar":{"spawnCap":2,"eliteNamePrefix":"Deep","enchantmentLevel":1,"darkness":true,"ambientSounds":true,"progressionTier":"mid"},"_section_battletowers":"=== Battle Towers ===","ba_bt:land_tower":{"spawnCap":8,"eliteChance":0.04,"eliteNamePrefix":"Corrupted","enchantmentLevel":3,"darkness":true,"ambientSounds":true,"persistentMobs":true,"armorTiers":["iron","gold","diamond"],"progressionTier":"late"},"ba_bt:ocean_tower":{"spawnCap":8,"eliteChance":0.04,"eliteNamePrefix":"Dread","enchantmentLevel":3,"darkness":true,"miningFatigue":true,"ambientSounds":true,"persistentMobs":true,"armorTiers":["iron","gold","diamond"],"progressionTier":"late"},"ba_bt:core_tower":{"spawnCap":10,"eliteChance":0.06,"eliteNamePrefix":"Corrupted","enchantmentLevel":4,"darkness":true,"miningFatigue":true,"slowness":true,"ambientSounds":true,"persistentMobs":true,"armorTiers":["iron","diamond","netherite"],"progressionTier":"veteran"},"_section_nether_expansion":"=== Jaden's Nether Expansion ===","netherexp:chapel":{"spawnCap":4,"eliteNamePrefix":"Fallen","enchantmentLevel":2,"darkness":true,"ambientSounds":true,"armorTiers":["iron","gold"],"progressionTier":"mid"},"netherexp:devils_bluff":{"spawnCap":5,"eliteNamePrefix":"Wither","enchantmentLevel":2,"armorTiers":["iron","gold"],"progressionTier":"mid"},"netherexp:mega_fossil":{"spawnCap":3,"eliteNamePrefix":"Cursed","enchantmentLevel":1,"ambientSounds":true,"progressionTier":"mid"},"netherexp:mega_fossil_campsite":{"spawnCap":4,"eliteNamePrefix":"Cursed","enchantmentLevel":1,"ambientSounds":true,"armorTiers":["chainmail","iron"],"progressionTier":"mid"},"netherexp:sanctum":{"spawnCap":8,"eliteChance":0.05,"eliteNamePrefix":"Fallen","enchantmentLevel":3,"darkness":true,"miningFatigue":true,"ambientSounds":true,"persistentMobs":true,"armorTiers":["iron","gold","diamond"],"progressionTier":"late"},"_section_ice_fire":"=== Ice and Fire ===","iceandfire:graveyard":{"spawnCap":4,"eliteNamePrefix":"Cursed","enchantmentLevel":1,"darkness":true,"ambientSounds":true,"armorTiers":["chainmail","iron"],"progressionTier":"mid"},"iceandfire:mausoleum":{"spawnCap":6,"eliteNamePrefix":"Dragonsworn","enchantmentLevel":2,"darkness":true,"miningFatigue":true,"ambientSounds":true,"armorTiers":["iron","gold"],"progressionTier":"late"},"iceandfire:gorgon_temple":{"spawnCap":5,"eliteNamePrefix":"Dragonsworn","enchantmentLevel":2,"darkness":true,"slowness":true,"ambientSounds":true,"armorTiers":["iron","gold"],"progressionTier":"late"},"_section_spellbooks":"=== Iron's Spellbooks ===","irons_spellbooks:pyromancer_tower":{"spawnCap":5,"eliteNamePrefix":"Arcane","enchantmentLevel":2,"darkness":true,"armorTiers":["iron","gold"],"progressionTier":"mid"},"irons_spellbooks:mountain_tower":{"spawnCap":5,"eliteNamePrefix":"Arcane","enchantmentLevel":2,"darkness":true,"armorTiers":["iron","gold"],"progressionTier":"mid"},"irons_spellbooks:mangrove_hut":{"spawnCap":2,"eliteNamePrefix":"Arcane","enchantmentLevel":1,"progressionTier":"early"},"irons_spellbooks:evoker_fort":{"spawnCap":8,"eliteChance":0.04,"eliteNamePrefix":"Arcane","enchantmentLevel":3,"darkness":true,"ambientSounds":true,"persistentMobs":true,"armorTiers":["iron","gold","diamond"],"progressionTier":"late"},"irons_spellbooks:impaled_icebreaker":{"spawnCap":4,"eliteNamePrefix":"Dread","enchantmentLevel":2,"armorTiers":["iron","gold"],"progressionTier":"mid"},"irons_spellbooks:ancient_battleground":{"spawnCap":6,"eliteNamePrefix":"Cursed","enchantmentLevel":2,"ambientSounds":true,"armorTiers":["iron","gold"],"progressionTier":"mid"},"irons_spellbooks:catacombs":{"spawnCap":6,"eliteNamePrefix":"Cursed","enchantmentLevel":3,"darkness":true,"miningFatigue":true,"ambientSounds":true,"armorTiers":["iron","gold"],"progressionTier":"late"},"_section_ars":"=== Ars Nouveau ===","ars_nouveau:guardian_wilden_den":{"spawnCap":4,"eliteNamePrefix":"Feral","enchantmentLevel":2,"darkness":true,"ambientSounds":true,"armorTiers":["chainmail","iron"],"progressionTier":"mid"},"ars_nouveau:hunter_wilden_den":{"spawnCap":4,"eliteNamePrefix":"Feral","enchantmentLevel":2,"darkness":true,"ambientSounds":true,"armorTiers":["chainmail","iron"],"progressionTier":"mid"},"ars_nouveau:stalker_wilden_den":{"spawnCap":4,"eliteNamePrefix":"Feral","enchantmentLevel":2,"darkness":true,"ambientSounds":true,"armorTiers":["chainmail","iron"],"progressionTier":"mid"},"_section_misc":"=== Miscellaneous Mods ===","galosphere:pink_salt_shrine":{"spawnCap":3,"eliteNamePrefix":"Arcane","enchantmentLevel":1,"darkness":true,"ambientSounds":true,"progressionTier":"mid"},"mowziesmobs:barako_village":{"spawnCap":5,"eliteNamePrefix":"Warchief","enchantmentLevel":1,"persistentMobs":true,"armorTiers":["leather","chainmail","iron"],"progressionTier":"mid"},"seavil:undersea_village":{"spawnCap":5,"eliteNamePrefix":"Dread","enchantmentLevel":1,"miningFatigue":true,"armorTiers":["chainmail","iron"],"progressionTier":"mid"},"_section_medieval_end":"=== Medieval End (IDs unconfirmed) ===","medievalend:end_castle":{"spawnCap":8,"eliteChance":0.04,"eliteNamePrefix":"Corrupted","enchantmentLevel":3,"darkness":true,"ambientSounds":true,"armorTiers":["iron","gold","diamond"],"progressionTier":"late"},"medievalend:end_keep":{"spawnCap":6,"eliteNamePrefix":"Corrupted","enchantmentLevel":3,"darkness":true,"armorTiers":["iron","gold"],"progressionTier":"late"},"medievalend:end_tower":{"spawnCap":4,"eliteNamePrefix":"Corrupted","enchantmentLevel":2,"darkness":true,"armorTiers":["iron","gold"],"progressionTier":"late"},"medievalend:end_shrine":{"spawnCap":3,"eliteNamePrefix":"Corrupted","enchantmentLevel":2,"ambientSounds":true,"progressionTier":"late"},"medievalend:end_ship":{"spawnCap":4,"eliteNamePrefix":"Corrupted","enchantmentLevel":2,"armorTiers":["iron","gold"],"progressionTier":"late"},"_section_unconfirmed":"=== Unconfirmed IDs (verify in-game) ===","taxcp:castle_pillager":{"spawnCap":8,"eliteChance":0.04,"eliteNamePrefix":"Commander","enchantmentLevel":2,"persistentMobs":true,"armorTiers":["iron","gold"],"progressionTier":"mid"},"goblins_tyranny:goblin_village":{"spawnCap":5,"eliteNamePrefix":"Warchief","enchantmentLevel":1,"persistentMobs":true,"armorTiers":["leather","chainmail"],"progressionTier":"early"},"goblins_tyranny:goblin_camp":{"spawnCap":3,"eliteNamePrefix":"Warchief","enchantmentLevel":0,"armorTiers":["leather","chainmail"],"progressionTier":"early"},"goblins_tyranny:goblin_watchtower":{"spawnCap":3,"eliteNamePrefix":"Warchief","enchantmentLevel":1,"armorTiers":["leather","chainmail"],"progressionTier":"early"},"goblins_tyranny:goblin_caravan":{"spawnCap":2,"enchantmentLevel":0,"progressionTier":"early"},"goblins_tyranny:goblin_cave":{"spawnCap":4,"eliteNamePrefix":"Warchief","enchantmentLevel":1,"darkness":true,"ambientSounds":true,"armorTiers":["leather","chainmail"],"progressionTier":"mid"},"theorcs:orc_camp":{"spawnCap":5,"eliteNamePrefix":"Warchief","enchantmentLevel":1,"persistentMobs":true,"armorTiers":["chainmail","iron"],"progressionTier":"mid"}}}